src/__init__.py
src/cli.py
src/infix_parser_test.py
src/lexer.py
src/lexer_test.py
src/parser.py
src/parser_test.py
pythoncalculator-1.0.0.dist-info/METADATA
pythoncalculator-1.0.0.dist-info/WHEEL
pythoncalculator-1.0.0.dist-info/entry_points.txt
pythoncalculator-1.0.0.dist-info/top_level.txt
pythoncalculator-1.0.0.dist-info/RECORD
